datarobot_dome/__init__.py
datarobot_dome/async_http_client.py
datarobot_dome/chat_helper.py
datarobot_dome/constants.py
datarobot_dome/drum_integration.py
datarobot_dome/guard.py
datarobot_dome/guard_executor.py
datarobot_dome/guard_helpers.py
datarobot_dome/guards/__init__.py
datarobot_dome/guards/guard_llm_mixin.py
datarobot_dome/llm.py
datarobot_dome/metrics/__init__.py
datarobot_dome/metrics/citation_metrics.py
datarobot_dome/metrics/factory.py
datarobot_dome/metrics/metric_scorer.py
datarobot_dome/pipeline/__init__.py
datarobot_dome/pipeline/llm_pipeline.py
datarobot_dome/pipeline/pipeline.py
datarobot_dome/pipeline/vdb_pipeline.py
datarobot_dome/runtime.py
datarobot_dome/streaming.py
datarobot_moderations-11.2.10.dist-info/METADATA
datarobot_moderations-11.2.10.dist-info/WHEEL
datarobot_moderations-11.2.10.dist-info/RECORD
