Metadata-Version: 2.4
Name: datarobot-moderations
Version: 11.2.10
Summary: DataRobot Monitoring and Moderation framework
License: DataRobot Tool and Utility Agreement
Author: DataRobot
Author-email: support@datarobot.com
Requires-Python: >=3.10,<3.13
Classifier: License :: Other/Proprietary License
Classifier: Programming Language :: Python :: 3
Classifier: Programming Language :: Python :: 3.10
Classifier: Programming Language :: Python :: 3.11
Classifier: Programming Language :: Python :: 3.12
Requires-Dist: aiohttp (>=3.9.5)
Requires-Dist: backoff (>=2.2.1)
Requires-Dist: datarobot (>=3.6.0)
Requires-Dist: datarobot-predict (>=1.9.6)
Requires-Dist: deepeval (>=3.3.5)
Requires-Dist: langchain (>=0.1.12)
Requires-Dist: langchain-nvidia-ai-endpoints (>=0.3.9)
Requires-Dist: langchain-openai (>=0.1.7)
Requires-Dist: llama-index (>=0.13.0)
Requires-Dist: llama-index-embeddings-azure-openai (>=0.1.6)
Requires-Dist: llama-index-llms-bedrock-converse (>=0.1.6)
Requires-Dist: llama-index-llms-langchain (>=0.1.3)
Requires-Dist: llama-index-llms-vertex (>=0.1.5)
Requires-Dist: nemoguardrails (>=0.9.0)
Requires-Dist: nest-asyncio (>=1.6.0)
Requires-Dist: numpy (>=1.25.0)
Requires-Dist: openai (>=1.14.3)
Requires-Dist: opentelemetry-api (>=1.16.0)
Requires-Dist: opentelemetry-instrumentation (>=0.60b1,<0.61)
Requires-Dist: opentelemetry-sdk (>=1.16.0)
Requires-Dist: pandas (>=2.0.3)
Requires-Dist: ragas (>=0.2.15)
Requires-Dist: rouge-score (>=0.1.2)
Requires-Dist: tiktoken (>=0.5.1)
Requires-Dist: trafaret (>=2.1.1)
